historicdutchweather/__init__.py
historicdutchweather/main.py
historicdutchweather/measuringstations.py
historicdutchweather-1.2.0.dist-info/METADATA
historicdutchweather-1.2.0.dist-info/WHEEL
historicdutchweather-1.2.0.dist-info/top_level.txt
historicdutchweather-1.2.0.dist-info/RECORD
